<mvc:View xmlns:core="sap.ui.core" xmlns:mvc="sap.ui.core.mvc" xmlns="sap.m"
	controllerName="vehicleLocator.controller.VehicleTrade_VehicleSelection" xmlns:l="sap.ui.layout" xmlns:form="sap.ui.layout.form"
	xmlns:uxap="sap.uxap"  xmlns:tnt="sap.tnt" xmlns:t="sap.ui.table" xmlns:u="sap.ui.unified" xmlns:f="sap.ui.layout.form" xmlns:html="http://www.w3.org/1999/xhtml">
	<App>
		<pages class="oImgsampl" height="200px">
			<Page showNavButton="false" enableScrolling="true">
				
				
				 				<customHeader>
					<Bar class="sapUiSmallPaddingBeginEnd clCustomHeaderBg">
						<contentLeft>
						
							<Image id="idLexusLogo" src="Images/toyota_logo_colour.png" width="100px"/>
							<Text text="|" class="sapUiTinyMarginBeginEnd"/>
							<Text class="clCustomFont" text="{i18n>PageTitle}"/>
						</contentLeft>
						<contentRight>
						 
									<!--<Button   class="VLbtn2" text="{i18n>Back}" type="Transparent" press="onNavBack" width="auto"/>-->
						<!--<Link text="{i18n>Back}" class="clCustomFont sapUiSmallMargin" press="handlebacksearch"/>-->
						</contentRight>
					</Bar>
				</customHeader>
				<!--<customHeader>-->
				<!--	<Bar class="sapUiSmallPaddingBeginEnd clCustomHeaderBg">-->
				<!--		<contentLeft>-->
				<!--			<Image id="idLexusLogo" src="Images/toyota_logo_colour.png" width="100px"/>-->
				<!--			<Text text="|" class="sapUiTinyMarginBeginEnd"/>-->
				<!--			<Text class="clCustomFont" text="{i18n>PageTitle}"/>-->
				<!--		</contentLeft>-->
				<!--		<contentRight>-->
				<!--			<Button text="{i18n>Logout}"/>-->
				<!--		</contentRight>-->
				<!--	</Bar>-->
				<!--</customHeader>-->
				<content>
					<tnt:ToolHeader>
		              	<Label id="oDealerCode4" width="auto"/>
						<Label id="oDealerOwnVehiSele" width="auto"/>
					<ToolbarSpacer/>
								<Button   class="VLbtn2" text="{i18n>Back}" type="Transparent" press="onNavBack" width="auto"/>
					</tnt:ToolHeader>
					<!--<Toolbar class="toolbar1">
						<ToolbarSpacer></ToolbarSpacer>
						</Toolbar>-->
						<!--	<Button text="Vehicle Locator" press="handleLinkPress"/>
						<Button text="Sold Order" press="handleLinkPress"/>
						<Button text="Price Protection" press="handleLinkPress"/>
						<Button text="Inventory Summary" press="handleLinkPress"/>
						<Button text="Sujjest Order" press="handleLinkPress"/>-->
					
					<VBox>
						<OverflowToolbar id="otb1">
							<Label text="{i18n>VehicleTrade-VehicleSelection}" width="auto" class="vHlabe1clss"/>
							<ToolbarSpacer/>
						</OverflowToolbar>
						<VBox>
							<HBox>
								<FlexBox width="40px"></FlexBox>
								<FlexBox height="100px" alignItems="Center" justifyContent="Center">
									<Label text="{i18n>Series}"/>
									<FlexBox width="7px"></FlexBox>
									<ComboBox placeholder="" width="140%" showSecondaryValues="true" filterSecondaryValues="true" selectionChange="handleoVt_SeriesChange"
										id="oVt_SeriesCmbo" items="{/}">
											<core:ListItem text="{=${SPRAS}==='English' ? ${TCISeriesDescriptionEN}:${TCISeriesDescriptionFR} }" key="{TCISeries}" additionalText=""/>
									</ComboBox>
									
				 
								<!--<ComboBox placeholder="" width="70%" showSecondaryValues="true" filterSecondaryValues="true" selectionChange="SeriesClickedVLS11"-->
								<!--	id="SeriesCmbo" items="{path:'/'}" change="handleSeriesChange">-->
								<!--	<core:ListItem text="{=${SPRAS}==='English' ? ${TCISeriesDescriptionEN}:${TCISeriesDescriptionFR} }" key="{TCISeries}" additionalText=""/>-->
								<!--</ComboBox>-->
																
									
									
									
									
									
									<!--	<SearchField width="215px" id="idVehclSerTrad"/>-->
								</FlexBox>
							</HBox>

		          <Table id="vehicleSelectTable" width="auto" class="sapUiResponsiveMargin" alternateRowColors="true" 
                   items="{
                    path: 'vehicleSelectTableModel>/',
                    sorter: {
                    path: 'zzadddata4',
                    descending: true
                    }
                    }"
                   noDataText="{i18n>NoData}"
                  

                   updateFinished="onUpdateFinished"
                   mode="None"
                   modeAnimationOn="true">

                <headerToolbar>
                    <OverflowToolbar id="otbSubheader">

                        <Title id="tableHeader1" text="{detailView>/tableCountSelect}"/>

                        <ToolbarSpacer/>
                       
                        <Button tooltip="Sort table by selected fields"  icon="sap-icon://sort"	
                                press="handleViewSettingsDialogButtonPressed" text="{i18n>Sorting}"/>
                    </OverflowToolbar>
                </headerToolbar>

                <columns>

                    <Column id="TradecolId" demandPopin="true" minScreenWidth="Tablet"   width="6rem"
                            hAlign="Left">
                        <Text text="{i18n>Select}" id="nameColumnTitle2"/>
                    </Column>
                    
                    <Column id="vehicleTrackNum" demandPopin="true" minScreenWidth="Tablet" hAlign="Center" width="6rem">
                        <Text text="{i18n>VehicleTrackingNumber}" wrapping="true"/>
                    </Column>
                    <Column id="series1" demandPopin="true" minScreenWidth="Tablet"  width="6rem"
                            hAlign="Center">
                        <Text text="{i18n>Series}"/>
                    </Column>
                    <Column id="model1"  demandPopin="true"  width="auto"
                            minScreenWidth="Tablet"  hAlign="Left">
                        <Text text="{i18n>Model}"/>
                    </Column>
                    <Column id="suffix1"   demandPopin="true"
                            minScreenWidth="Tablet" width="auto">
                        <Text text="{i18n>Suffix}" id="nameColumnTitle1"/>
                    </Column>
                       <Column id="color1"  demandPopin="true" minScreenWidth="Tablet">
                        <Text text="{i18n>Color}"/>
                    </Column>  
                    <Column id="apx1"  demandPopin="true"  
                            minScreenWidth="Tablet" width="3rem">
                        <Text text="{i18n>APX}" />
                    </Column>

                    <Column id="ordertype1"   hAlign="Center" demandPopin="true"
                            minScreenWidth="Tablet">
                        <Text text="{i18n>OrderType}" />
                    </Column>
                    <Column id="etafrom1"   demandPopin="true" minScreenWidth="Tablet">
                        <Text text="{i18n>ETAFrom}" />
                    </Column>
                    <Column id="etato1"  demandPopin="true" minScreenWidth="Tablet" width="5rem" hAlign="Center">
                        <Text text="{i18n>ETATo}"  wrapping="true"/>
                    </Column>
                     
                </columns>

                <items>
                   <ColumnListItem type="Active" press="oTradeLinkPress" id="onlinkPress">
                        <cells>
       
                        	
                           	<Link id="selectId" text="{i18n>Select}"  class="link" subtle="true" press="oTradeLinkPress" wrapping="false"  />
 
                           		<Text text="{vehicleSelectTableModel>zzvtn}" wrapping="false" width="6rem" id="zzvtnid" />
 		

                           			<Text text="{=${languageModel>/SPRAS}==='English' ? ${vehicleSelectTableModel>zzseries_desc_en}:${vehicleSelectTableModel>zzseries_desc_fr} }" id="oSeries" />

                                		<Text text="{vehicleSelectTableModel>matnr} - {=${languageModel>/SPRAS}==='English' ? ${vehicleSelectTableModel>model_desc_en}:${vehicleSelectTableModel>model_desc_fr} }" id="oZmodel" />
                                
                              
 <Text text="{vehicleSelectTableModel>zzsuffix} - {=${languageModel>/SPRAS}==='English' ? ${vehicleSelectTableModel>suffix_desc_en}:${vehicleSelectTableModel>suffix_desc_fr} }/{=${languageModel>/SPRAS}==='English' ? ${vehicleSelectTableModel>mrktg_int_desc_en}:${vehicleSelectTableModel>mrktg_int_desc_fr} }" id="oZsuffix"	/>	                               
              
  	<Text text="{vehicleSelectTableModel>zzextcol} - {=${languageModel>/SPRAS}==='English' ? ${vehicleSelectTableModel>mktg_desc_en}:${vehicleSelectTableModel>mktg_desc_fr} }" width="auto" wrapping="false"   />             
              
              
                                <Text text="{vehicleSelectTableModel>zzapx}"   width="3rem" wrapping="false"/>
  
                                
                                 <Text text="{path:'vehicleSelectTableModel>zzordertype',formatter:'vehicleLocator.Formatter.Formatter.OrderType'}"  width="6rem" wrapping="false" visible="{vehicleSelectTableModel>/noDisplayOrderType}"/>
                                 
                                  <Text text="{path:'vehicleSelectTableModel>zzadddata4',formatter:'vehicleLocator.Formatter.Formatter.VehicleSelectoinEtaFromDate1'}"  width="6rem" wrapping="false"/>   
                              
                              <Text text="{path:'vehicleSelectTableModel>pstsp',formatter:'vehicleLocator.Formatter.Formatter.TradeSummaryoDate1'}" width="6rem" wrapping="false"/>    

                        </cells>
                    </ColumnListItem>
                </items>
            </Table>			
	
		
					
					</VBox>
					<FlexBox height="100px" id="PagintionFlexId" alignItems="Center" justifyContent="End">
						<items></items>
					</FlexBox>
				</VBox>
			</content>
		</Page>
	</pages>
</App>
</mvc:View>