<mvc:View xmlns:core="sap.ui.core" xmlns:mvc="sap.ui.core.mvc" xmlns="sap.m" controllerName="vehicleLocator.controller.VehicleTrade_Summary"
	xmlns:l="sap.ui.layout" xmlns:form="sap.ui.layout.form" xmlns:uxap="sap.uxap" xmlns:t="sap.ui.table" xmlns:u="sap.ui.unified"
	xmlns:f="sap.ui.layout.form" xmlns:html="http://www.w3.org/1999/xhtml">
	<App>
		<pages class="oImgsampl" height="200px">
			<Page showNavButton="false" navButtonPress="onBack">
				<customHeader>
					<Bar class="sapUiSmallPaddingBeginEnd clCustomHeaderBg">
						<contentLeft>
							<Image id="idLexusLogo" src="Images/Lexus.png" width="100px"/>
							<Text text="|" class="sapUiTinyMarginBeginEnd"/>
							<Text class="clCustomFont" text="Vehicle Locator-Trade"/>
						</contentLeft>
						<contentRight>
							<Button text="Logout"/>
						</contentRight>
					</Bar>
				</customHeader>
				<content>
					<Toolbar class="toolbar3">
						<Label text="" width="180px" class="vTlabe1clss"/>
						<ToolbarSpacer></ToolbarSpacer>
						<!--<Button text="Vehicle Locator" press="handleLinkPress"/>
						<Button text="Sold Order" press="handleLinkPress"/>
						<Button text="Price Protection" press="handleLinkPress"/>
						<Button text="Inventory Summary" press="handleLinkPress"/>
						<Button text="Sujjest Order" press="handleLinkPress"/>-->
					</Toolbar>
					<VBox class="sapUiSmallMargin">
						<OverflowToolbar id="otb1">
							<Label text="Trade Summary" width="200px" class="vHlabe1clss"/>
							<ToolbarSpacer/>
						</OverflowToolbar>
					</VBox>
					<HBox>
						<FlexBox width="40px"></FlexBox>
						<FlexBox height="35px" alignItems="Center" justifyContent="Center">
							<Label text="My Trade Requests" class="flexdontclabllist"/>
						</FlexBox>
					</HBox>
					<VBox>
						<!--	<OverflowToolbar id="otb1">
							<Label text="My Trade Requests" width="200px" class="vHlabe1clss"/>
							<ToolbarSpacer/>
						</OverflowToolbar>-->
						<VBox>
							<Table id="tableVTSum" width="auto" class="sapUiResponsiveMargin" items="{/}" growingThreshold="150">
								<columns>
									<Column minScreenWidth="Desktop" demandPopin="true" hAlign="Center">
										<Text text="Request"/>
									</Column>
									<Column minScreenWidth="Desktop" demandPopin="true" hAlign="Center">
										<Text text="Created"/>
									</Column>
									<Column minScreenWidth="Desktop" demandPopin="true" hAlign="Center">
										<Text text="Dealer"/>
									</Column>
									<Column minScreenWidth="Desktop" demandPopin="true" hAlign="Center">
										<Text text="Model"/>
									</Column>
									<Column minScreenWidth="Desktop" demandPopin="true">
										<Text text="Suffix"/>
									</Column>
									<Column minScreenWidth="Desktop" demandPopin="true">
										<Text text="Trade in Return"/>
									</Column>
									<Column minScreenWidth="Desktop" demandPopin="true">
										<Text text="Status"/>
									</Column>
									<Column minScreenWidth="Desktop" demandPopin="true">
										<Text text="Status Updated Date"/>
									</Column>
								</columns>
								<items>
									<ColumnListItem press="onLineItemPressedtree1" type="Navigation">
										<cells>
											<ObjectIdentifier title="{}"/>
											<Text text="{}"/>
											<Text text="{}"/>
											<Text text="{}"/>
											<Text text="{}"/>
											<Text text="{}"/>
											<Text text="{}"/>
											<Text text="{}"/>
										</cells>
									</ColumnListItem>
								</items>
							</Table>
						</VBox>
					</VBox>
					<HBox>
						<FlexBox width="40px"></FlexBox>
						<FlexBox height="25px" alignItems="Center" justifyContent="Center">
							<Label text="Received Trade Requests" class="flexdontclabllist"/>
							<!--<FlexBox width="960px"></FlexBox>
							<Button text="Delete"/>-->
						</FlexBox>
					</HBox>
					<Table id="tableVrade" width="auto" class="sapUiResponsiveMargin" items="{/}" growingThreshold="150">
						<columns>
							<Column minScreenWidth="Desktop" demandPopin="true" hAlign="Center">
								<Text text="Request"/>
							</Column>
							<Column minScreenWidth="Desktop" demandPopin="true" hAlign="Center">
								<Text text="From Dealer"/>
							</Column>
							<Column minScreenWidth="Desktop" demandPopin="true">
								<Text text="Model"/>
							</Column>
							<Column minScreenWidth="Desktop" demandPopin="true">
								<Text text="Suffix"/>
							</Column>
							<Column minScreenWidth="Desktop" demandPopin="true">
								<Text text="Trade in Return"/>
							</Column>
							<Column minScreenWidth="Desktop" demandPopin="true">
								<Text text="Status"/>
							</Column>
						</columns>
						<items>
							<ColumnListItem press="onLineItemPressedtree1" type="Navigation">
								<cells>
									<Text text="{}"/>
									<Text text="{}"/>
									<Text text="{}"/>
									<Text text="{}"/>
									<Text text="{}"/>
									<Text text="{}"/>
								</cells>
							</ColumnListItem>
						</items>
					</Table>
				</content>
			</Page>
		</pages>
	</App>
</mvc:View>